{
  "version": 2,
  "taskId": "67af4c1cc0e59d55e2010b97",
  "nameKo": "A Life Lesson",
  "nameEn": "A Life Lesson",
  "steps": [
    "프라퍼(Prapor)에게서 'A Life Lesson' 퀘스트를 수락한다.",
    "퀘스트 목표는 다음 세 가지 주류 아이템을 지정된 수량만큼 수집하여 프라퍼에게 전달하는 것이다: 타르코프스카야 보드카(Tarkovskaya vodka) 8병, 댄 재키엘 위스키(Dan Jackiel whiskey) 15병, 피어스 해치링 문샤인(Fierce Hatchling moonshine) 15병.",
    "각 아이템은 레이드 내에서 획득할 수 없으며, 주로 트레이더 구매 또는 플리마켓에서 구입해야 한다.",
    "타르코프스카야 보드카는 주로 테라피스트(Therapist)와 피스키퍼(Peacekeeper) 트레이더가 판매하며, 댄 재키엘 위스키와 피어스 해치링 문샤인은 메카닉(Mechanic) 또는 다른 트레이더가 판매할 수 있으니 확인한다.",
    "플리마켓을 활용해 부족한 아이템을 구매하거나, 트레이더의 재고를 주기적으로 확인하여 필요한 수량을 확보한다.",
    "모든 아이템을 수집한 후 프라퍼에게 돌아가 아이템을 전달하고 퀘스트를 완료한다."
  ],
  "sourceUrl": "https://escapefromtarkov.fandom.com/wiki/A_Life_Lesson",
  "license": "CC BY-SA",
  "generatedAt": "2026-06-18T18:56:19.643+09:00"
}
